django_documentdb/__init__.py
django_documentdb/aggregates.py
django_documentdb/base.py
django_documentdb/client.py
django_documentdb/compiler.py
django_documentdb/creation.py
django_documentdb/dbapi.py
django_documentdb/expressions.py
django_documentdb/features.py
django_documentdb/functions.py
django_documentdb/introspection.py
django_documentdb/lookups.py
django_documentdb/models.py
django_documentdb/operations.py
django_documentdb/query.py
django_documentdb/query_utils.py
django_documentdb/schema.py
django_documentdb/utils.py
django_documentdb/fields/__init__.py
django_documentdb/fields/auto.py
django_documentdb/fields/duration.py
django_documentdb/fields/json.py
django_documentdb-0.0.13.dist-info/licenses/LICENSE
django_documentdb-0.0.13.dist-info/METADATA
django_documentdb-0.0.13.dist-info/WHEEL
django_documentdb-0.0.13.dist-info/top_level.txt
django_documentdb-0.0.13.dist-info/RECORD
