Metadata-Version: 2.4
Name: django-documentdb
Version: 0.0.13
Summary: DocumentDB/MongoDB backend for Django
Author: The MongoDB Python Team, iYasha
License:                                  Apache License
Project-URL: Documentation, https://django-documentdb.readthedocs.io
Project-URL: Source, https://github.com/iYasha/django-documentdb
Project-URL: Tracker, https://github.com/iYasha/django-documentdb/issues
Keywords: mongo,mongodb,documentdb,pymongo,django
Classifier: Development Status :: 2 - Pre-Alpha
Classifier: Framework :: Django
Classifier: Framework :: Django :: 5.0
Classifier: Intended Audience :: Developers
Classifier: License :: OSI Approved :: Apache Software License
Classifier: Operating System :: OS Independent
Classifier: Programming Language :: Python :: 3
Classifier: Programming Language :: Python :: 3 :: Only
Classifier: Programming Language :: Python :: 3.10
Classifier: Programming Language :: Python :: 3.11
Classifier: Programming Language :: Python :: 3.12
Requires-Python: >=3.10
License-File: LICENSE
Requires-Dist: django<5.3,>=5.0
Requires-Dist: pymongo<5.0,>=4.6
Provides-Extra: docs
Requires-Dist: sphinx>=7; extra == "docs"
Dynamic: license-file
